cuPymysql/__init__.py
cuPymysql/main.py
cuPymysql/utils.py
cuPymysql-0.0.3.dist-info/METADATA
cuPymysql-0.0.3.dist-info/WHEEL
cuPymysql-0.0.3.dist-info/top_level.txt
cuPymysql-0.0.3.dist-info/RECORD
