Metadata-Version: 2.1
Name: cuPymysql
Version: 0.0.3
Summary: Instead of PyMySQL
Author: davek
Author-email: hwangdoyeouyu@gmail.com
Requires-Python: >=3.6
